atek/__init__.py
atek/data_loaders/__init__.py
atek/data_loaders/atek_raw_dataloader_as_cubercnn.py
atek/data_loaders/atek_wds_dataloader.py
atek/data_loaders/cubercnn_model_adaptor.py
atek/data_preprocess/__init__.py
atek/data_preprocess/atek_data_sample.py
atek/data_preprocess/atek_wds_writer.py
atek/data_preprocess/genera_atek_preprocessor_factory.py
atek/data_preprocess/general_atek_preprocessor.py
atek/data_preprocess/processors/__init__.py
atek/data_preprocess/processors/aria_camera_processor.py
atek/data_preprocess/processors/depth_image_processor.py
atek/data_preprocess/processors/efm_gt_processor.py
atek/data_preprocess/processors/mps_online_calib_processor.py
atek/data_preprocess/processors/mps_semidense_processor.py
atek/data_preprocess/processors/mps_traj_processor.py
atek/data_preprocess/processors/obb2_gt_processor.py
atek/data_preprocess/processors/obb3_gt_processor.py
atek/data_preprocess/sample_builders/__init__.py
atek/data_preprocess/sample_builders/atek_data_paths_provider.py
atek/data_preprocess/sample_builders/efm_sample_builder.py
atek/data_preprocess/sample_builders/obb_sample_builder.py
atek/data_preprocess/subsampling_lib/__init__.py
atek/data_preprocess/subsampling_lib/temporal_subsampler.py
atek/data_preprocess/util/__init__.py
atek/viz/__init__.py
atek/viz/atek_visualizer.py
atek/viz/cubercnn_visualizer.py
atek_v1/__init__.py
atek_v1/data_preprocess/__init__.py
atek_v1/data_preprocess/adt_gt_data_processor.py
atek_v1/data_preprocess/base_gt_data_processor.py
atek_v1/data_preprocess/data_schema.py
atek_v1/data_preprocess/data_utils.py
atek_v1/data_preprocess/frame_data_processor.py
atek_v1/data_preprocess/frameset_aligner.py
atek_v1/data_preprocess/frameset_group_generator.py
atek_v1/data_preprocess/mps_data_processor.py
atek_v1/data_preprocess/webdataset_writer.py
atek_v1/dataset/__init__.py
atek_v1/dataset/atek_raw_dataset.py
atek_v1/dataset/atek_webdataset.py
atek_v1/dataset/dataset_factory.py
atek_v1/dataset/omni3d_adapter.py
atek_core-0.3.4.dist-info/LICENSE
atek_core-0.3.4.dist-info/METADATA
atek_core-0.3.4.dist-info/WHEEL
atek_core-0.3.4.dist-info/top_level.txt
atek_core-0.3.4.dist-info/RECORD
